gravity/__init__.py
gravity/account.py
gravity/aes.py
gravity/amount.py
gravity/asset.py
gravity/bet.py
gravity/bettingmarket.py
gravity/bettingmarketgroup.py
gravity/block.py
gravity/blockchain.py
gravity/blockchainobject.py
gravity/committee.py
gravity/event.py
gravity/eventgroup.py
gravity/exceptions.py
gravity/gravity.py
gravity/instance.py
gravity/memo.py
gravity/message.py
gravity/notify.py
gravity/proposal.py
gravity/rule.py
gravity/sport.py
gravity/storage.py
gravity/transactionbuilder.py
gravity/utils.py
gravity/wallet.py
gravity/witness.py
gravity/cli/__init__.py
gravity/cli/account.py
gravity/cli/bookie.py
gravity/cli/cli.py
gravity/cli/committee.py
gravity/cli/decorators.py
gravity/cli/info.py
gravity/cli/main.py
gravity/cli/message.py
gravity/cli/proposal.py
gravity/cli/rpc.py
gravity/cli/ui.py
gravity/cli/wallet.py
gravity/cli/witness.py
gravity_protocol-0.1.33.dist-info/METADATA
gravity_protocol-0.1.33.dist-info/RECORD
gravity_protocol-0.1.33.dist-info/WHEEL
gravity_protocol-0.1.33.dist-info/entry_points.txt
gravity_protocol-0.1.33.dist-info/top_level.txt
gravityapi/__init__.py
gravityapi/exceptions.py
gravityapi/node.py
gravityapi/wallet.py
gravityapi/websocket.py
gravitybase/__init__.py
gravitybase/account.py
gravitybase/asset_permissions.py
gravitybase/chains.py
gravitybase/memo.py
gravitybase/objects.py
gravitybase/objecttypes.py
gravitybase/operationids.py
gravitybase/operations.py
gravitybase/signedtransactions.py
gravitybase/transactions.py
gravitybase/types.py
